fm2prof/__init__.py
fm2prof/__main__.py
fm2prof/cli.py
fm2prof/common.py
fm2prof/configurationfile_template.json
fm2prof/cross_section.py
fm2prof/data_import.py
fm2prof/export.py
fm2prof/fm2prof_runner.py
fm2prof/ini_file.py
fm2prof/mask_output_file.py
fm2prof/nearest_neighbour.py
fm2prof/polygon_file.py
fm2prof/utils.py
fm2prof/lib/polysimplify.README.md
fm2prof/lib/polysimplify.py
fm2prof-2.4.0.dist-info/METADATA
fm2prof-2.4.0.dist-info/WHEEL
fm2prof-2.4.0.dist-info/licenses/LICENSE.txt
fm2prof-2.4.0.dist-info/licenses/LICENSE_HEADER.txt
fm2prof-2.4.0.dist-info/RECORD
