Metadata-Version: 2.4
Name: fm2prof
Version: 2.4.0
Author-email: Koen Berends <koen.berends@deltares.nl>
License-Expression: GPL-3.0-or-later AND LGPL-3.0-or-later
License-File: LICENSE.txt
License-File: LICENSE_HEADER.txt
Requires-Python: <3.13,>=3.10
Requires-Dist: click~=8.1
Requires-Dist: colorama>=0.4.6
Requires-Dist: geojson~=3.1
Requires-Dist: matplotlib<4,>=3.8.0
Requires-Dist: meshkernel>=8.1.2
Requires-Dist: netcdf4<2,>=1.6.0
Requires-Dist: notebook<8,>=7.1.2
Requires-Dist: numpy~=1.26
Requires-Dist: pandas<3,>=2.2.1
Requires-Dist: pip>=25.1.1
Requires-Dist: scikit-learn<2,>=1.3.0
Requires-Dist: scipy~=1.11
Requires-Dist: shapely~=2.0
Requires-Dist: tqdm<5,>=4.64.0
Requires-Dist: typer<0.10,>=0.9.0
Requires-Dist: xarray>=2025.6.1
